gitArch/__init__.py
gitArch/arch.py
gitArch/defaults.py
gitArch/git.py
gitArch/tools.py
gitArch-0.1.dist-info/LICENSE
gitArch-0.1.dist-info/METADATA
gitArch-0.1.dist-info/WHEEL
gitArch-0.1.dist-info/top_level.txt
gitArch-0.1.dist-info/RECORD
