Metadata-Version: 2.1
Name: gitArch
Version: 0.1
Summary: A tool to handle server's git repositories
Home-page: https://github.com/divad1196/gitArch
Author: Gallay David
Author-email: davidtennis96@hotmail.com
License: UNKNOWN
Platform: UNKNOWN
Classifier: Programming Language :: Python :: 3
Classifier: License :: OSI Approved :: MIT License
Classifier: Operating System :: OS Independent
